setup.py
distributions_05_dsnd/Binomialdistribution.py
distributions_05_dsnd/Gaussiandistribution.py
distributions_05_dsnd/Generaldistribution.py
distributions_05_dsnd/__init__.py
distributions_05_dsnd.egg-info/PKG-INFO
distributions_05_dsnd.egg-info/SOURCES.txt
distributions_05_dsnd.egg-info/dependency_links.txt
distributions_05_dsnd.egg-info/not-zip-safe
distributions_05_dsnd.egg-info/top_level.txt